{"nodes":[{"content":"providers","pos":[11,20]},{"content":"providers","pos":[34,43]},{"content":"providers","pos":[232,241]},{"content":"Displays available providers and groups.","pos":[244,284]},{"content":"Remarks","pos":[397,404]},{"content":"This option queries all installed/known and registered providers, as well as all known kernel flags and groups.","pos":[407,518]},{"content":"The options in the following table are supported.","pos":[520,569]},{"content":"Option","pos":[674,680]},{"content":"Description","pos":[690,701]},{"content":"I, Installed","pos":[762,774]},{"content":"Includes installed/known providers.","pos":[800,835]},{"content":"R, Registered","pos":[884,897]},{"content":"Includes registered providers.","pos":[923,953]},{"content":"KF, KernelFlags","pos":[1001,1016]},{"content":"Includes kernel flags.","pos":[1042,1064]},{"content":"KG, KernelGroups","pos":[1113,1129]},{"content":"Includes kernel groups.","pos":[1155,1178]},{"content":"K, Kernel","pos":[1226,1235]},{"content":"Includes kernel flags and groups; shortcut for <ph id=\"ph1\">&amp;quot;</ph>KF KG<ph id=\"ph2\">&amp;quot;</ph>.","pos":[1261,1326]},{"content":"If no options are specified, all providers are included in the output.","pos":[1364,1434]},{"content":"Related topics","pos":[1439,1453]},{"content":"Xperf Options","pos":[1457,1470]}],"content":"---\ntitle: providers\ndescription: providers\nMSHAttr:\n- 'PreferredSiteName:MSDN'\n- 'PreferredLib:/library/windows/hardware'\nms.assetid: 19c60e7c-2673-4e7c-9b04-978ac94ce812\nms.prod: W10\nms.mktglfcycl: operate\nms.sitesec: msdn\n---\n\n# providers\n\n\nDisplays available providers and groups.\n\n``` syntax\nxperf -providers [Installed|I] [Registered|R] [KernelFlags|KF] [KernelGroups|KG] [Kernel|K]\n```\n\n## Remarks\n\n\nThis option queries all installed/known and registered providers, as well as all known kernel flags and groups.\n\nThe options in the following table are supported.\n\n<table>\n<colgroup>\n<col width=\"50%\" />\n<col width=\"50%\" />\n</colgroup>\n<thead>\n<tr class=\"header\">\n<th>Option</th>\n<th>Description</th>\n</tr>\n</thead>\n<tbody>\n<tr class=\"odd\">\n<td><p><strong>I, Installed</strong></p></td>\n<td><p>Includes installed/known providers.</p></td>\n</tr>\n<tr class=\"even\">\n<td><p><strong>R, Registered</strong></p></td>\n<td><p>Includes registered providers.</p></td>\n</tr>\n<tr class=\"odd\">\n<td><p><strong>KF, KernelFlags</strong></p></td>\n<td><p>Includes kernel flags.</p></td>\n</tr>\n<tr class=\"even\">\n<td><p><strong>KG, KernelGroups</strong></p></td>\n<td><p>Includes kernel groups.</p></td>\n</tr>\n<tr class=\"odd\">\n<td><p><strong>K, Kernel</strong></p></td>\n<td><p>Includes kernel flags and groups; shortcut for &quot;KF KG&quot;.</p></td>\n</tr>\n</tbody>\n</table>\n\n \n\nIf no options are specified, all providers are included in the output.\n\n## Related topics\n\n\n[Xperf Options](xperf-options.md)\n\n \n\n \n\n\n\n\n\n\n\n"}