{"nodes":[{"content":"Download WinPE (Windows PE)","pos":[35,62]},{"content":"Download WinPE (Windows PE)","pos":[171,198]},{"content":"Download WinPE (Windows PE)","pos":[207,234]},{"content":"Download Windows PE (WinPE) to boot your PC to a command prompt.","pos":[237,301]},{"content":"You can install Windows PE to a USB flash drive, CD, DVD, or virtual hard drive.","pos":[302,382]},{"pos":[513,536],"content":"Install the Windows ADK"},{"content":"To download the correct version of Windows PE for your PC, you’ll need to download and install the Windows ADK.","pos":[539,650]},{"content":"The instructions to install Windows PE vary depending on the media.","pos":[651,718]},{"pos":[720,861],"content":"Download the <bpt id=\"p1\">[</bpt>Windows Assessment and Deployment Kit (ADK)<ept id=\"p1\">](http://go.microsoft.com/fwlink/?LinkId=526803)</ept> and install the following features:"},{"pos":[867,947],"content":"<bpt id=\"p1\">**</bpt>Deployment Tools<ept id=\"p1\">**</ept>: includes the <bpt id=\"p2\">**</bpt>Deployment and Imaging Tools Environment<ept id=\"p2\">**</ept>."},{"pos":[953,1041],"content":"<bpt id=\"p1\">**</bpt>Windows Preinstallation Environment<ept id=\"p1\">**</ept> : includes the files used to install Windows PE."},{"pos":[1205,1239],"content":"Create a bootable USB, CD, or DVD:"},{"pos":[1242,1406],"content":"See <bpt id=\"p1\">[</bpt>WinPE: Create USB Bootable drive<ept id=\"p1\">](winpe-create-usb-bootable-drive.md)</ept> or <bpt id=\"p2\">[</bpt>WinPE: Create a Boot CD, DVD, ISO, or VHD<ept id=\"p2\">](winpe-create-a-boot-cd-dvd-iso-or-vhd.md)</ept>."},{"pos":[1444,1458],"content":"Related topics"},{"content":"WinPE for Windows 10","pos":[1462,1482]},{"content":"WinPE: Mount and Customize","pos":[1502,1528]}],"content":"---\nauthor: Justinha\nDescription: 'Download WinPE (Windows PE)'\nms.assetid: e1b5bcac-761f-4efb-9288-a20da1086446\nMSHAttr: 'PreferredLib:/library/windows/hardware'\ntitle: 'Download WinPE (Windows PE)'\n---\n\n# Download WinPE (Windows PE)\n\n\nDownload Windows PE (WinPE) to boot your PC to a command prompt. You can install Windows PE to a USB flash drive, CD, DVD, or virtual hard drive.\n\n## <span id=\"Install_the_Windows_ADK\"></span><span id=\"install_the_windows_adk\"></span><span id=\"INSTALL_THE_WINDOWS_ADK\"></span>Install the Windows ADK\n\n\nTo download the correct version of Windows PE for your PC, you’ll need to download and install the Windows ADK. The instructions to install Windows PE vary depending on the media.\n\nDownload the [Windows Assessment and Deployment Kit (ADK)](http://go.microsoft.com/fwlink/?LinkId=526803) and install the following features:\n\n-   **Deployment Tools**: includes the **Deployment and Imaging Tools Environment**.\n\n-   **Windows Preinstallation Environment** : includes the files used to install Windows PE.\n\n## <span id=\"Create_a_bootable_USB__CD__or_DVD_\"></span><span id=\"create_a_bootable_usb__cd__or_dvd_\"></span><span id=\"CREATE_A_BOOTABLE_USB__CD__OR_DVD_\"></span>Create a bootable USB, CD, or DVD:\n\n\nSee [WinPE: Create USB Bootable drive](winpe-create-usb-bootable-drive.md) or [WinPE: Create a Boot CD, DVD, ISO, or VHD](winpe-create-a-boot-cd-dvd-iso-or-vhd.md).\n\n## <span id=\"related_topics\"></span>Related topics\n\n\n[WinPE for Windows 10](winpe-intro.md)\n\n[WinPE: Mount and Customize](winpe-mount-and-customize.md)\n\n \n\n \n\n\n\n\n\n\n"}