{"nodes":[{"content":"Windows 10 deployment tools reference (Windows 10)","pos":[11,61]},{"content":"Learn about the tools available to deploy Windows 10.","pos":[75,128]},{"content":"Windows 10 deployment tools reference","pos":[261,298]},{"content":"Learn about the tools available to deploy Windows 10.","pos":[301,354]},{"content":"In this section","pos":[359,374]},{"content":"Topic","pos":[493,498]},{"content":"Description","pos":[521,532]},{"content":"Windows 10 deployment tools","pos":[599,626]},{"content":"To successfully deploy the Windows 10 operating system and applications for your organization, it is essential that you know about the available tools to help with the process.","pos":[700,876]},{"content":"In this topic, you will learn about the most commonly used tools for Windows 10 deployment.","pos":[877,968]},{"content":"Windows ADK for Windows 10 scenarios for IT Pros","pos":[1023,1071]},{"content":"The Windows Assessment and Deployment Kit (Windows ADK) contains tools that can be used by IT Pros to deploy Windows.","pos":[1140,1257]},{"content":"Volume Activation Management Tool (VAMT) Technical Reference","pos":[1311,1371]},{"content":"The Volume Activation Management Tool (VAMT) enables network administrators and other IT professionals to automate and centrally manage the Windows速, Microsoft速 Office, and select other Microsoft products volume and retail-activation process.","pos":[1440,1682]},{"content":"User State Migration Tool (USMT) Technical Reference","pos":[1737,1789]},{"content":"The User State Migration Tool (USMT) 10.0 is included with the Windows Assessment and Deployment Kit (Windows ADK) for Windows 10.","pos":[1849,1979]},{"content":"USMT provides a highly customizable user-profile migration experience for IT professionals.","pos":[1980,2071]}],"content":"---\ntitle: Windows 10 deployment tools reference (Windows 10)\ndescription: Learn about the tools available to deploy Windows 10.\nms.assetid: 5C4B0AE3-B2D0-4628-9E73-606F3FAA17BB\nms.prod: w10\nms.mktglfcycl: deploy\nms.sitesec: library\nauthor: greg-lindsay\n---\n\n# Windows 10 deployment tools reference\n\n\nLearn about the tools available to deploy Windows 10.\n\n## In this section\n\n\n<table>\n<colgroup>\n<col width=\"50%\" />\n<col width=\"50%\" />\n</colgroup>\n<thead>\n<tr class=\"header\">\n<th align=\"left\">Topic</th>\n<th align=\"left\">Description</th>\n</tr>\n</thead>\n<tbody>\n<tr class=\"odd\">\n<td align=\"left\"><p>[Windows 10 deployment tools](windows-deployment-scenarios-and-tools.md)</p></td>\n<td align=\"left\"><p>To successfully deploy the Windows 10 operating system and applications for your organization, it is essential that you know about the available tools to help with the process. In this topic, you will learn about the most commonly used tools for Windows 10 deployment.</p></td>\n</tr>\n<tr class=\"even\">\n<td align=\"left\"><p>[Windows ADK for Windows 10 scenarios for IT Pros](windows-adk-scenarios-for-it-pros.md)</p></td>\n<td align=\"left\"><p>The Windows Assessment and Deployment Kit (Windows ADK) contains tools that can be used by IT Pros to deploy Windows.</p></td>\n</tr>\n<tr class=\"odd\">\n<td align=\"left\"><p>[Volume Activation Management Tool (VAMT) Technical Reference](volume-activation-management-tool.md)</p></td>\n<td align=\"left\"><p>The Volume Activation Management Tool (VAMT) enables network administrators and other IT professionals to automate and centrally manage the Windows速, Microsoft速 Office, and select other Microsoft products volume and retail-activation process.</p></td>\n</tr>\n<tr class=\"even\">\n<td align=\"left\"><p>[User State Migration Tool (USMT) Technical Reference](usmt-technical-reference.md)</p></td>\n<td align=\"left\"><p>The User State Migration Tool (USMT) 10.0 is included with the Windows Assessment and Deployment Kit (Windows ADK) for Windows 10. USMT provides a highly customizable user-profile migration experience for IT professionals.</p></td>\n</tr>\n</tbody>\n</table>\n\n \n\n \n\n \n\n\n\n\n\n"}