{"nodes":[{"content":"Use the <ph id=\"ph1\">\\[</ph>ConnectionSettings<ph id=\"ph2\">\\]</ph> .INS file setting to specify the network connection settings needed to install your custom package.","pos":[17,147]},{"content":"Use the ConnectionSettings .INS file to review the network connections for install (Internet Explorer Administration Kit 11 for IT Pros)","pos":[277,413]},{"content":"Use the ConnectionSettings .INS file to review the network connections for install","pos":[421,503]},{"content":"Info about the network connection settings used to install your custom package.","pos":[504,583]},{"content":"This section creates a common configuration on all of your employee’s computers.","pos":[584,664]},{"content":"Name","pos":[667,671]},{"content":"Value","pos":[679,684]},{"content":"Description","pos":[707,718]},{"content":"ConnectName0","pos":[779,791]},{"content":"Name for the connection.","pos":[814,838]},{"content":"ConnectName1","pos":[842,854]},{"content":"Secondary name for the connection.","pos":[877,911]},{"content":"DeleteConnectionSettings","pos":[915,939]},{"content":"<bpt id=\"p1\">**</bpt>0.<ept id=\"p1\">**</ept> Don’t remove the connection settings during installation.","pos":[949,1013]},{"content":"<bpt id=\"p1\">**</bpt>1.<ept id=\"p1\">**</ept> Remove the connection settings during installation.","pos":[1022,1080]},{"content":"Note","pos":[1085,1089]},{"content":"This only appears for the <bpt id=\"p1\">**</bpt>Internal<ept id=\"p1\">**</ept> version of the IEAK 11.","pos":[1095,1157]},{"content":"Determines whether to remove the existing connection settings during installation of your custom package.","pos":[1169,1274]},{"content":"Option","pos":[1278,1284]},{"content":"<bpt id=\"p1\">**</bpt>0.<ept id=\"p1\">**</ept> Don’t let employees import connection settings.","pos":[1294,1348]},{"content":"<bpt id=\"p1\">**</bpt>1.<ept id=\"p1\">**</ept> Let employees import connection settings.","pos":[1357,1405]},{"content":"Determines whether an employee can import connection settings into the Internet Explorer Customization Wizard.","pos":[1417,1527]}],"content":"---\ndescription: Use the \\[ConnectionSettings\\] .INS file setting to specify the network connection settings needed to install your custom package.\nms.assetid: 41410300-6ddd-43b2-b9e2-0108a2221355\nauthor: eross-msft\nms.prod: ie11\nms.mktglfcycl: plan\nms.sitesec: library\ntitle: Use the ConnectionSettings .INS file to review the network connections for install (Internet Explorer Administration Kit 11 for IT Pros)\n---\n\n# Use the ConnectionSettings .INS file to review the network connections for install\nInfo about the network connection settings used to install your custom package. This section creates a common configuration on all of your employee’s computers.\n\n|Name       |Value                      |Description  |\n|-----------|---------------------------|-------------|\n|ConnectName0 |`<connection_name>` |Name for the connection. |\n|ConnectName1 |`<connection_name>` |Secondary name for the connection. |\n|DeleteConnectionSettings |<ul><li>**0.** Don’t remove the connection settings during installation.</li><li>**1.** Remove the connection settings during installation.<p>**Note**<br>This only appears for the **Internal** version of the IEAK 11.</li></ul> |Determines whether to remove the existing connection settings during installation of your custom package. |\n|Option |<ul><li>**0.** Don’t let employees import connection settings.</li><li>**1.** Let employees import connection settings.</li></ul> |Determines whether an employee can import connection settings into the Internet Explorer Customization Wizard. |"}