{"nodes":[{"content":"Use VAMT in Windows PowerShell (Windows 10)","pos":[11,54]},{"content":"Use VAMT in Windows PowerShell","pos":[68,98]},{"content":"Use VAMT in Windows PowerShell","pos":[252,282]},{"content":"The Volume Activation Management Tool (VAMT) PowerShell cmdlets can be used to perform the same functions as the Vamt.exe command-line tool.","pos":[284,424]},{"content":"To install PowerShell 3.0","pos":[427,452]},{"content":"VAMT PowerShell cmdlets require Windows PowerShell, which is included in Windows 10, Windows 8 and Windows Server® 2012.","pos":[459,579]},{"content":"You can download PowerShell for Windows 7 or other operating systems from the <bpt id=\"p1\">[</bpt>Microsoft Download Center<ept id=\"p1\">](http://go.microsoft.com/fwlink/p/?LinkId=218356)</ept>.","pos":[580,735]},{"content":"To install the Windows Assessment and Deployment Kit","pos":[738,790]},{"content":"In addition to PowerShell, you must import the VAMT PowerShell module.","pos":[797,867]},{"content":"The module is included in the VAMT 3.0 folder after you install the Windows Assessment and Deployment Kit (Windows ADK).","pos":[868,988]},{"content":"To prepare the VAMT PowerShell environment","pos":[991,1033]},{"content":"To open PowerShell with administrative credentials, click <bpt id=\"p1\">**</bpt>Start<ept id=\"p1\">**</ept> and type “PowerShell” to locate the program.","pos":[1040,1152]},{"content":"Right-click <bpt id=\"p1\">**</bpt>Windows PowerShell<ept id=\"p1\">**</ept>, and then click <bpt id=\"p2\">**</bpt>Run as administrator<ept id=\"p2\">**</ept>.","pos":[1153,1229]},{"content":"To open PowerShell in Windows 7, click <bpt id=\"p1\">**</bpt>Start<ept id=\"p1\">**</ept>, click <bpt id=\"p2\">**</bpt>All Programs<ept id=\"p2\">**</ept>, click <bpt id=\"p3\">**</bpt>Accessories<ept id=\"p3\">**</ept>, click <bpt id=\"p4\">**</bpt>Windows PowerShell<ept id=\"p4\">**</ept>, right-click <bpt id=\"p5\">**</bpt>Windows PowerShell<ept id=\"p5\">**</ept>, and then click <bpt id=\"p6\">**</bpt>Run as administrator<ept id=\"p6\">**</ept>.","pos":[1230,1433]},{"pos":[1439,1741],"content":"**Important**  \nIf you are using a computer that has an 64-bit processor, select **Windows PowerShell (x86)**. VAMT PowerShell cmdlets are supported for the x86 architecture only. You must use an x86 version of Windows PowerShell to import the VAMT module, which are available in these directories:","leadings":["","    "],"nodes":[{"content":"Important","pos":[2,11]},{"content":"If you are using a computer that has an 64-bit processor, select **Windows PowerShell (x86)**. VAMT PowerShell cmdlets are supported for the x86 architecture only. You must use an x86 version of Windows PowerShell to import the VAMT module, which are available in these directories:","pos":[16,298],"nodes":[{"content":"If you are using a computer that has an 64-bit processor, select <bpt id=\"p1\">**</bpt>Windows PowerShell (x86)<ept id=\"p1\">**</ept>.","pos":[0,94]},{"content":"VAMT PowerShell cmdlets are supported for the x86 architecture only.","pos":[95,163]},{"content":"You must use an x86 version of Windows PowerShell to import the VAMT module, which are available in these directories:","pos":[164,282]}]}]},{"content":"The x86 version of PowerShell is available in C:<ph id=\"ph1\">\\\\</ph>Windows<ph id=\"ph2\">\\\\</ph>SysWOW64<ph id=\"ph3\">\\\\</ph>WindowsPowerShell<ph id=\"ph4\">\\\\</ph>v1.0<ph id=\"ph5\">\\\\</ph>powershell.exe","pos":[1750,1858]},{"content":"The x86 version of the PowerShell ISE is available in C:<ph id=\"ph1\">\\\\</ph>Windows<ph id=\"ph2\">\\\\</ph>SysWOW64<ph id=\"ph3\">\\\\</ph>WindowsPowerShell<ph id=\"ph4\">\\\\</ph>v1.0<ph id=\"ph5\">\\\\</ph>powershell<ph id=\"ph6\">\\_</ph>ise.exe","pos":[1867,1988]},{"content":"For all supported operating systems you can use the VAMT PowerShell module included with the Windows ADK.","pos":[1993,2098]},{"content":"By default, the module is installed with the Windows ADK in the VAMT folder.","pos":[2099,2175]},{"content":"Change directories to the directory where VAMT is located.","pos":[2176,2234]},{"pos":[2240,2358],"content":"For example, if the Windows ADK is installed in the default location of <ph id=\"ph1\">`C:\\Program Files(x86)\\Windows Kits\\10`</ph>, type:"},{"content":"Import the VAMT PowerShell module.","pos":[2475,2509]},{"content":"To import the module, type the following at a command prompt:","pos":[2510,2571]},{"content":"Where <bpt id=\"p1\">**</bpt>Import-Module<ept id=\"p1\">**</ept> imports a module only into the current session.","pos":[2629,2700]},{"content":"To import the module into all sessions, add an <bpt id=\"p1\">**</bpt>Import-Module<ept id=\"p1\">**</ept> command to a Windows PowerShell profile.","pos":[2701,2806]},{"content":"For more information about profiles, type <ph id=\"ph1\">`get-help about_profiles`</ph>.","pos":[2807,2875]},{"content":"To Get Help for VAMT PowerShell cmdlets","pos":[2880,2919]},{"content":"You can view all of the help sections for a VAMT PowerShell cmdlet, or you can view only the section that you are interested in.","pos":[2921,3049]},{"content":"To view all of the Help content for a VAMT cmdlet, type:","pos":[3050,3106]},{"content":"For example, type:","pos":[3147,3165]},{"content":"Warning","pos":[3211,3218]},{"content":"The update-help cmdlet is not supported for VAMT PowerShell cmdlets.","pos":[3223,3291]},{"content":"To view online help for VAMT cmdlets, you can use the -online option with the get-help cmdlet.","pos":[3292,3386]},{"content":"For more information, see <bpt id=\"p1\">[</bpt>Volume Activation Management Tool (VAMT) Cmdlets in Windows PowerShell<ept id=\"p1\">](http://go.microsoft.com/fwlink/p/?LinkId=242278)</ept>.","pos":[3387,3535]},{"content":"To view VAMT PowerShell Help sections","pos":[3539,3576]},{"content":"To get the syntax to use with a cmdlet, type the following at a command prompt:","pos":[3584,3663]},{"content":"For example, type:","pos":[3715,3733]},{"content":"To see examples using a cmdlet, type:","pos":[3788,3825]},{"content":"For example, type:","pos":[3887,3905]}],"content":"---\ntitle: Use VAMT in Windows PowerShell (Windows 10)\ndescription: Use VAMT in Windows PowerShell\nms.assetid: 13e0ceec-d827-4681-a5c3-8704349e3ba9\nms.prod: w10\nms.mktglfcycl: deploy\nms.sitesec: library\nms.pagetype: activation\nauthor: jdeckerMS\n---\n\n# Use VAMT in Windows PowerShell\n\nThe Volume Activation Management Tool (VAMT) PowerShell cmdlets can be used to perform the same functions as the Vamt.exe command-line tool.\n**To install PowerShell 3.0**\n-   VAMT PowerShell cmdlets require Windows PowerShell, which is included in Windows 10, Windows 8 and Windows Server® 2012. You can download PowerShell for Windows 7 or other operating systems from the [Microsoft Download Center](http://go.microsoft.com/fwlink/p/?LinkId=218356).\n**To install the Windows Assessment and Deployment Kit**\n-   In addition to PowerShell, you must import the VAMT PowerShell module. The module is included in the VAMT 3.0 folder after you install the Windows Assessment and Deployment Kit (Windows ADK).\n**To prepare the VAMT PowerShell environment**\n1.  To open PowerShell with administrative credentials, click **Start** and type “PowerShell” to locate the program. Right-click **Windows PowerShell**, and then click **Run as administrator**. To open PowerShell in Windows 7, click **Start**, click **All Programs**, click **Accessories**, click **Windows PowerShell**, right-click **Windows PowerShell**, and then click **Run as administrator**.\n\n    **Important**  \n    If you are using a computer that has an 64-bit processor, select **Windows PowerShell (x86)**. VAMT PowerShell cmdlets are supported for the x86 architecture only. You must use an x86 version of Windows PowerShell to import the VAMT module, which are available in these directories:\n    -   The x86 version of PowerShell is available in C:\\\\Windows\\\\SysWOW64\\\\WindowsPowerShell\\\\v1.0\\\\powershell.exe\n    -   The x86 version of the PowerShell ISE is available in C:\\\\Windows\\\\SysWOW64\\\\WindowsPowerShell\\\\v1.0\\\\powershell\\_ise.exe\n2.  For all supported operating systems you can use the VAMT PowerShell module included with the Windows ADK. By default, the module is installed with the Windows ADK in the VAMT folder. Change directories to the directory where VAMT is located.\n\n    For example, if the Windows ADK is installed in the default location of `C:\\Program Files(x86)\\Windows Kits\\10`, type:\n    \n    ``` ps1\n    cd “C:\\Program Files (x86)\\Windows Kits\\10\\Assessment and Deployment Kit\\VAMT 3.0”\n    ```\n3.  Import the VAMT PowerShell module. To import the module, type the following at a command prompt:\n    ``` syntax\n    Import-Module .\\VAMT.psd1\n    ```\n    Where **Import-Module** imports a module only into the current session. To import the module into all sessions, add an **Import-Module** command to a Windows PowerShell profile. For more information about profiles, type `get-help about_profiles`.\n\n## To Get Help for VAMT PowerShell cmdlets\n\nYou can view all of the help sections for a VAMT PowerShell cmdlet, or you can view only the section that you are interested in. To view all of the Help content for a VAMT cmdlet, type:\n``` ps1\nget-help <cmdlet name> -all\n```\nFor example, type:\n``` ps1\nget-help get-VamtProduct -all\n```\n\n**Warning**  \nThe update-help cmdlet is not supported for VAMT PowerShell cmdlets. To view online help for VAMT cmdlets, you can use the -online option with the get-help cmdlet. For more information, see [Volume Activation Management Tool (VAMT) Cmdlets in Windows PowerShell](http://go.microsoft.com/fwlink/p/?LinkId=242278).\n\n**To view VAMT PowerShell Help sections**\n\n1.  To get the syntax to use with a cmdlet, type the following at a command prompt:\n    ``` ps1\n    get-help <cmdlet name>\n    ```\n    For example, type:\n    ``` ps1\n    get-help get-VamtProduct \n    ```\n2.  To see examples using a cmdlet, type:\n    ``` ps1\n    get-help <cmdlet name> -examples\n    ```\n    For example, type:\n    ``` ps1\n    get-help get-VamtProduct -examples\n    ```\n"}